etl/__init__.py
etl-0.0.1.dist-info/METADATA
etl-0.0.1.dist-info/RECORD
etl-0.0.1.dist-info/WHEEL
etl-0.0.1.dist-info/entry_points.txt
etl-0.0.1.dist-info/top_level.txt
