Metadata-Version: 2.1
Name: etl
Version: 0.0.1
Summary: etl
Home-page: UNKNOWN
Author: UNKNOWN
Author-email: UNKNOWN
License: MIT license
Platform: UNKNOWN
Classifier: Development Status :: 2 - Pre-Alpha
Classifier: Intended Audience :: Developers
Classifier: License :: OSI Approved :: MIT License
Classifier: Natural Language :: English
Classifier: Programming Language :: Python :: 3
Classifier: Programming Language :: Python :: 3.6
